google_translate_py/__init__.py
google_translate_py/main.py
google_translate.py-1.0.0.dist-info/LICENSE
google_translate.py-1.0.0.dist-info/METADATA
google_translate.py-1.0.0.dist-info/WHEEL
google_translate.py-1.0.0.dist-info/top_level.txt
google_translate.py-1.0.0.dist-info/RECORD
