Metadata-Version: 2.1
Name: google-translate.py
Version: 1.0.0
Summary: Library for using accurate Google Translate in Python
Home-page: https://github.com/Takkun053/google-translate.py
Author: Takkun053
Author-email: takkun.053@gmail.com
License: MIT license
Keywords: Google_Translate
Platform: UNKNOWN
Classifier: Development Status :: 5 - Production/Stable
Classifier: Intended Audience :: Developers
Classifier: License :: OSI Approved :: MIT License
Classifier: Natural Language :: English
Classifier: Natural Language :: Japanese
Classifier: Programming Language :: Python
Classifier: Programming Language :: Python :: 3
Classifier: Programming Language :: Python :: 3.6
Classifier: Programming Language :: Python :: 3.7
Classifier: Programming Language :: Python :: 3.8
Classifier: Programming Language :: Python :: 3.9
Requires-Python: >=3.6
